llama_index/tools/cassandra/__init__.py
llama_index/tools/cassandra/base.py
llama_index/tools/cassandra/cassandra_database_wrapper.py
llama_index_tools_cassandra-0.4.1.dist-info/METADATA
llama_index_tools_cassandra-0.4.1.dist-info/WHEEL
llama_index_tools_cassandra-0.4.1.dist-info/licenses/LICENSE
llama_index_tools_cassandra-0.4.1.dist-info/RECORD
