Metadata-Version: 2.4
Name: llama-index-tools-cassandra
Version: 0.4.1
Summary: llama-index tools Apache Cassandra® integration
Author-email: Patrick McFadin <patrick@datastax.com>
License-Expression: MIT
License-File: LICENSE
Requires-Python: <4.0,>=3.9
Requires-Dist: cassio<0.2,>=0.1.7
Requires-Dist: llama-index-core<0.15,>=0.13.0
